mouseauth-client/__init__.py
mouseauth-client/clients.py
mouseauth-client/fullapi.py
mouseauth_client/__init__.py
mouseauth_client/clients.py
mouseauth_client/fullapi.py
mouthauth-client/__init__.py
mouthauth-client/clients.py
mouthauth-client/fullapi.py
mouseauth_client-1.0.4.dist-info/METADATA
mouseauth_client-1.0.4.dist-info/WHEEL
mouseauth_client-1.0.4.dist-info/top_level.txt
mouseauth_client-1.0.4.dist-info/RECORD
