Metadata-Version: 2.4
Name: MouseAuth-Client
Version: 1.0.4
Summary: MouseAuth Client for Python
Author: LacyCat
Classifier: Programming Language :: Python :: 3
Requires-Python: >=3.10
Requires-Dist: requests>=2.28.0
Requires-Dist: numpy>=1.21.0
Requires-Dist: typing-extensions>=4.0.0
Dynamic: author
Dynamic: classifier
Dynamic: requires-dist
Dynamic: requires-python
Dynamic: summary
